parq_tools/__init__.py
parq_tools/calculated_columns.py
parq_tools/lazy_parquet.py
parq_tools/parq_compare.py
parq_tools/parq_concat.py
parq_tools/parq_filter.py
parq_tools/parq_profile.py
parq_tools/parq_schema_tools.py
parq_tools/utils/__init__.py
parq_tools/utils/_query_parser.py
parq_tools/utils/archive_utils.py
parq_tools/utils/demo_block_model.py
parq_tools/utils/file_utils.py
parq_tools/utils/hash_utils.py
parq_tools/utils/index_utils.py
parq_tools/utils/memory_utils.py
parq_tools/utils/metadata_utils.py
parq_tools/utils/optional_imports.py
parq_tools/utils/profile_utils.py
parq_tools/utils/progress.py
parq_tools-0.3.1.dist-info/LICENSE
parq_tools-0.3.1.dist-info/METADATA
parq_tools-0.3.1.dist-info/WHEEL
parq_tools-0.3.1.dist-info/RECORD
