Metadata-Version: 2.3
Name: parq-tools
Version: 0.3.1
Summary: A collection of utilities for efficiently working with **large-scale** Parquet datasets.
Author: Greg
Author-email: 11791585+elphick@users.noreply.github.com
Requires-Python: >=3.10,<3.13
Classifier: Programming Language :: Python :: 3
Classifier: Programming Language :: Python :: 3.10
Classifier: Programming Language :: Python :: 3.11
Classifier: Programming Language :: Python :: 3.12
Provides-Extra: blockmodel
Provides-Extra: profiling
Provides-Extra: progress
Requires-Dist: lark (>=1.2.2,<2.0.0)
Requires-Dist: pyarrow (>=16.0)
Requires-Dist: pyvista (>=0.45.2,<0.46.0) ; extra == "blockmodel"
Requires-Dist: setuptools ; extra == "profiling"
Requires-Dist: tqdm (>=4.67.1,<5.0.0) ; extra == "progress"
Requires-Dist: ydata-profiling (>=4.16.1,<5.0.0) ; extra == "profiling"
